<?xml version="1.0" encoding="utf-16"?>
<BtxtFile xmlns:xsi="http://www.w3.org/2001/XMLSchema-instance" xmlns:xsd="http://www.w3.org/2001/XMLSchema">
  <NumberOfLabels>100</NumberOfLabels>
  <NumberOfStrings>100</NumberOfStrings>
  <Labels>
    <BtxtLabel>
      <Key>ITEM_TEXT_000</Key>
      <Values>
        <BtxtString>
          <Id>524551</Id>
          <Value>ダミーテキスト</Value>
        </BtxtString>
      </Values>
    </BtxtLabel>
    <BtxtLabel>
      <Key>ITEM_TEXT_001</Key>
      <Values>
        <BtxtString>
          <Id>19399436</Id>
          <Value>ᜀ自分᠀じぶんᤀのバッテリーと
アプモンのＨＰを
５００ᜀ回復᠀かいふくᤀさせる</Value>
        </BtxtString>
      </Values>
    </BtxtLabel>
    <BtxtLabel>
      <Key>ITEM_TEXT_002</Key>
      <Values>
        <BtxtString>
          <Id>36307725</Id>
          <Value>ᜀ自分᠀じぶんᤀのバッテリーと
アプモンのＨＰを
１５００ᜀ回復᠀かいふくᤀさせる</Value>
        </BtxtString>
      </Values>
    </BtxtLabel>
    <BtxtLabel>
      <Key>ITEM_TEXT_003</Key>
      <Values>
        <BtxtString>
          <Id>53084941</Id>
          <Value>ᜀ自分᠀じぶんᤀのバッテリーと
アプモンのＨＰを
４０００ᜀ回復᠀かいふくᤀさせる</Value>
        </BtxtString>
      </Values>
    </BtxtLabel>
    <BtxtLabel>
      <Key>ITEM_TEXT_004</Key>
      <Values>
        <BtxtString>
          <Id>69731084</Id>
          <Value>ᜀ自分᠀じぶんᤀのバッテリーと
アプモンのＨＰを
ᜀ全回復᠀ぜんかいふくᤀさせる</Value>
        </BtxtString>
      </Values>
    </BtxtLabel>
    <BtxtLabel>
      <Key>ITEM_TEXT_005</Key>
      <Values>
        <BtxtString>
          <Id>85852691</Id>
          <Value>ᜀ自分᠀じぶんᤀのᜀ必殺技᠀ひっさつわざᤀゲージを
ためる</Value>
        </BtxtString>
      </Values>
    </BtxtLabel>
    <BtxtLabel>
      <Key>ITEM_TEXT_006</Key>
      <Values>
        <BtxtString>
          <Id>103154195</Id>
          <Value>ᜀ自分᠀じぶんᤀのᜀ必殺技᠀ひっさつわざᤀゲージを
ᜀ大᠀おおᤀきく　ためる</Value>
        </BtxtString>
      </Values>
    </BtxtLabel>
    <BtxtLabel>
      <Key>ITEM_TEXT_007</Key>
      <Values>
        <BtxtString>
          <Id>120193555</Id>
          <Value>ᜀ自分᠀じぶんᤀのᜀ必殺技᠀ひっさつわざᤀゲージを
ᜀ最大᠀さいだいᤀまで　ためる</Value>
        </BtxtString>
      </Values>
    </BtxtLabel>
    <BtxtLabel>
      <Key>ITEM_TEXT_008</Key>
      <Values>
        <BtxtString>
          <Id>136839699</Id>
          <Value>ᜀ自分᠀じぶんᤀのアプモンの
ᜀ状態異常᠀じょうたいいじょうᤀを　ᜀ治᠀なおᤀす</Value>
        </BtxtString>
      </Values>
    </BtxtLabel>
    <BtxtLabel>
      <Key>ITEM_TEXT_009</Key>
      <Values>
        <BtxtString>
          <Id>153616914</Id>
          <Value>ᜀ自分᠀じぶんᤀのロックされたᜀ手札᠀てふだᤀを
すべてᜀ解放᠀かいほうᤀする</Value>
        </BtxtString>
      </Values>
    </BtxtLabel>
    <BtxtLabel>
      <Key>ITEM_TEXT_010</Key>
      <Values>
        <BtxtString>
          <Id>169083402</Id>
          <Value>ᜀ自分᠀じぶんᤀのデッキを
リセットする</Value>
        </BtxtString>
      </Values>
    </BtxtLabel>
    <BtxtLabel>
      <Key>ITEM_TEXT_011</Key>
      <Values>
        <BtxtString>
          <Id>188351251</Id>
          <Value>ヒフミがᜀ丘᠀おかᤀの　コンビニᜀ前᠀まえᤀにいる
ガシャモンの　アプモンガシャを
１ᜀ回᠀かいᤀまわせるチケット</Value>
        </BtxtString>
      </Values>
    </BtxtLabel>
    <BtxtLabel>
      <Key>ITEM_TEXT_012</Key>
      <Values>
        <BtxtString>
          <Id>205128467</Id>
          <Value>ヒフミがᜀ丘᠀おかᤀの　コンビニᜀ前᠀まえᤀにいる
ガシャモンの　超アプモンガシャを
１ᜀ回᠀かいᤀまわせるチケット</Value>
        </BtxtString>
      </Values>
    </BtxtLabel>
    <BtxtLabel>
      <Key>ITEM_TEXT_013</Key>
      <Values>
        <BtxtString>
          <Id>221905683</Id>
          <Value>ヒフミがᜀ丘᠀おかᤀの　コンビニᜀ前᠀まえᤀにいる
ガシャモンの　極アプモンガシャを
１ᜀ回᠀かいᤀまわせるチケット</Value>
        </BtxtString>
      </Values>
    </BtxtLabel>
    <BtxtLabel>
      <Key>ITEM_TEXT_014</Key>
      <Values>
        <BtxtString>
          <Id>236585481</Id>
          <Value>アプモン１ᜀ体᠀たいᤀを
ウィルスᜀ化᠀かᤀさせる</Value>
        </BtxtString>
      </Values>
    </BtxtLabel>
    <BtxtLabel>
      <Key>ITEM_TEXT_015</Key>
      <Values>
        <BtxtString>
          <Id>254018066</Id>
          <Value>ウィルスᜀ化᠀かᤀした　アプモン１ᜀ体᠀たいᤀを
ᜀ元᠀もとᤀにもどす</Value>
        </BtxtString>
      </Values>
    </BtxtLabel>
    <BtxtLabel>
      <Key>ITEM_TEXT_016</Key>
      <Values>
        <BtxtString>
          <Id>270139918</Id>
          <Value>アプモンのメジャーＶｅｒ．を
1つ　ᜀ上᠀あᤀげる</Value>
        </BtxtString>
      </Values>
    </BtxtLabel>
    <BtxtLabel>
      <Key>ITEM_TEXT_017</Key>
      <Values>
        <BtxtString>
          <Id>287572751</Id>
          <Value>アプモンの
ソーシャルのᜀ属性値᠀ぞくせいちᤀを
１つ　ᜀ上᠀あᤀげる</Value>
        </BtxtString>
      </Values>
    </BtxtLabel>
    <BtxtLabel>
      <Key>ITEM_TEXT_018</Key>
      <Values>
        <BtxtString>
          <Id>304087820</Id>
          <Value>アプモンの
ナビのᜀ属性値᠀ぞくせいちᤀを
１つ　ᜀ上᠀あᤀげる</Value>
        </BtxtString>
      </Values>
    </BtxtLabel>
    <BtxtLabel>
      <Key>ITEM_TEXT_019</Key>
      <Values>
        <BtxtString>
          <Id>320996110</Id>
          <Value>アプモンの
システムのᜀ属性値᠀ぞくせいちᤀを
１つ　ᜀ上᠀あᤀげる</Value>
        </BtxtString>
      </Values>
    </BtxtLabel>
    <BtxtLabel>
      <Key>ITEM_TEXT_020</Key>
      <Values>
        <BtxtString>
          <Id>337773326</Id>
          <Value>アプモンの
エンタメのᜀ属性値᠀ぞくせいちᤀを
１つ　ᜀ上᠀あᤀげる</Value>
        </BtxtString>
      </Values>
    </BtxtLabel>
    <BtxtLabel>
      <Key>ITEM_TEXT_021</Key>
      <Values>
        <BtxtString>
          <Id>354550541</Id>
          <Value>アプモンの
ライフのᜀ属性値᠀ぞくせいちᤀを
１つ　ᜀ上᠀あᤀげる</Value>
        </BtxtString>
      </Values>
    </BtxtLabel>
    <BtxtLabel>
      <Key>ITEM_TEXT_022</Key>
      <Values>
        <BtxtString>
          <Id>371327757</Id>
          <Value>アプモンの
ツールのᜀ属性値᠀ぞくせいちᤀを
１つ　ᜀ上᠀あᤀげる</Value>
        </BtxtString>
      </Values>
    </BtxtLabel>
    <BtxtLabel>
      <Key>ITEM_TEXT_023</Key>
      <Values>
        <BtxtString>
          <Id>388104973</Id>
          <Value>アプモンの
ゲームのᜀ属性値᠀ぞくせいちᤀを
１つ　ᜀ上᠀あᤀげる</Value>
        </BtxtString>
      </Values>
    </BtxtLabel>
    <BtxtLabel>
      <Key>ITEM_TEXT_024</Key>
      <Values>
        <BtxtString>
          <Id>404620047</Id>
          <Value>アプモンの
ソーシャルのᜀ属性値᠀ぞくせいちᤀを
０にする</Value>
        </BtxtString>
      </Values>
    </BtxtLabel>
    <BtxtLabel>
      <Key>ITEM_TEXT_025</Key>
      <Values>
        <BtxtString>
          <Id>421135116</Id>
          <Value>アプモンの
ナビのᜀ属性値᠀ぞくせいちᤀを
０にする</Value>
        </BtxtString>
      </Values>
    </BtxtLabel>
    <BtxtLabel>
      <Key>ITEM_TEXT_026</Key>
      <Values>
        <BtxtString>
          <Id>438043406</Id>
          <Value>アプモンの
システムのᜀ属性値᠀ぞくせいちᤀを
０にする</Value>
        </BtxtString>
      </Values>
    </BtxtLabel>
    <BtxtLabel>
      <Key>ITEM_TEXT_027</Key>
      <Values>
        <BtxtString>
          <Id>454820622</Id>
          <Value>アプモンの
エンタメのᜀ属性値᠀ぞくせいちᤀを
０にする</Value>
        </BtxtString>
      </Values>
    </BtxtLabel>
    <BtxtLabel>
      <Key>ITEM_TEXT_028</Key>
      <Values>
        <BtxtString>
          <Id>471597837</Id>
          <Value>アプモンの
ライフのᜀ属性値᠀ぞくせいちᤀを
０にする</Value>
        </BtxtString>
      </Values>
    </BtxtLabel>
    <BtxtLabel>
      <Key>ITEM_TEXT_029</Key>
      <Values>
        <BtxtString>
          <Id>488375053</Id>
          <Value>アプモンの
ツールのᜀ属性値᠀ぞくせいちᤀを
０にする</Value>
        </BtxtString>
      </Values>
    </BtxtLabel>
    <BtxtLabel>
      <Key>ITEM_TEXT_030</Key>
      <Values>
        <BtxtString>
          <Id>505152269</Id>
          <Value>アプモンの
ゲームのᜀ属性値᠀ぞくせいちᤀを
０にする</Value>
        </BtxtString>
      </Values>
    </BtxtLabel>
    <BtxtLabel>
      <Key>ITEM_TEXT_031</Key>
      <Values>
        <BtxtString>
          <Id>522584593</Id>
          <Value>ＡＲダンジョンをクリアしたᜀ証᠀あかしᤀ
たくさん　ᜀ集᠀あつᤀめると…？</Value>
        </BtxtString>
      </Values>
    </BtxtLabel>
    <BtxtLabel>
      <Key>ITEM_TEXT_032</Key>
      <Values>
        <BtxtString>
          <Id>539886350</Id>
          <Value>アプモンデータラボが
ᜀ発行᠀はっこうᤀしているチケット
たくさん　ᜀ集᠀あつᤀめると…？</Value>
        </BtxtString>
      </Values>
    </BtxtLabel>
    <BtxtLabel>
      <Key>ITEM_TEXT_033</Key>
      <Values>
        <BtxtString>
          <Id>556532493</Id>
          <Value>ᜀ広告᠀こうこくᤀを　ᜀ消᠀けᤀすと
もらえるポイント
たくさん　ᜀ集᠀あつᤀめると…？</Value>
        </BtxtString>
      </Values>
    </BtxtLabel>
    <BtxtLabel>
      <Key>ITEM_TEXT_034</Key>
      <Values>
        <BtxtString>
          <Id>573440786</Id>
          <Value>レースモンとの
レースでᜀ獲得᠀かくとくᤀできる　フラッグ
たくさん　ᜀ集᠀あつᤀめると…？</Value>
        </BtxtString>
      </Values>
    </BtxtLabel>
    <BtxtLabel>
      <Key>ITEM_TEXT_035</Key>
      <Values>
        <BtxtString>
          <Id>589824531</Id>
          <Value>スターターＧＰ　ブロンズに
ᜀ挑戦᠀ちょうせんᤀすることができるᜀ証᠀あかしᤀ</Value>
        </BtxtString>
      </Values>
    </BtxtLabel>
    <BtxtLabel>
      <Key>ITEM_TEXT_036</Key>
      <Values>
        <BtxtString>
          <Id>606601747</Id>
          <Value>スターターＧＰ　シルバーに
ᜀ挑戦᠀ちょうせんᤀすることができるᜀ証᠀あかしᤀ</Value>
        </BtxtString>
      </Values>
    </BtxtLabel>
    <BtxtLabel>
      <Key>ITEM_TEXT_037</Key>
      <Values>
        <BtxtString>
          <Id>623378963</Id>
          <Value>スターターＧＰ　ゴールドに
ᜀ挑戦᠀ちょうせんᤀすることができるᜀ証᠀あかしᤀ</Value>
        </BtxtString>
      </Values>
    </BtxtLabel>
    <BtxtLabel>
      <Key>ITEM_TEXT_038</Key>
      <Values>
        <BtxtString>
          <Id>640418575</Id>
          <Value>これを　ᜀ持᠀もᤀっていると
Ｆランクマスターに
ᜀ挑戦᠀ちょうせんᤀすることができる</Value>
        </BtxtString>
      </Values>
    </BtxtLabel>
    <BtxtLabel>
      <Key>ITEM_TEXT_039</Key>
      <Values>
        <BtxtString>
          <Id>657195791</Id>
          <Value>これを　ᜀ持᠀もᤀっていると
Ｅランクマスターに
ᜀ挑戦᠀ちょうせんᤀすることができる</Value>
        </BtxtString>
      </Values>
    </BtxtLabel>
    <BtxtLabel>
      <Key>ITEM_TEXT_040</Key>
      <Values>
        <BtxtString>
          <Id>673973007</Id>
          <Value>これを　ᜀ持᠀もᤀっていると
Ｄランクマスターに
ᜀ挑戦᠀ちょうせんᤀすることができる</Value>
        </BtxtString>
      </Values>
    </BtxtLabel>
    <BtxtLabel>
      <Key>ITEM_TEXT_041</Key>
      <Values>
        <BtxtString>
          <Id>690750223</Id>
          <Value>これを　ᜀ持᠀もᤀっていると
Ｃランクマスターに
ᜀ挑戦᠀ちょうせんᤀすることができる</Value>
        </BtxtString>
      </Values>
    </BtxtLabel>
    <BtxtLabel>
      <Key>ITEM_TEXT_042</Key>
      <Values>
        <BtxtString>
          <Id>707527439</Id>
          <Value>これを　ᜀ持᠀もᤀっていると
Ｂランクマスターに
ᜀ挑戦᠀ちょうせんᤀすることができる</Value>
        </BtxtString>
      </Values>
    </BtxtLabel>
    <BtxtLabel>
      <Key>ITEM_TEXT_043</Key>
      <Values>
        <BtxtString>
          <Id>724304655</Id>
          <Value>これを　ᜀ持᠀もᤀっていると
Ａランクマスターに
ᜀ挑戦᠀ちょうせんᤀすることができる</Value>
        </BtxtString>
      </Values>
    </BtxtLabel>
    <BtxtLabel>
      <Key>ITEM_TEXT_044</Key>
      <Values>
        <BtxtString>
          <Id>740950803</Id>
          <Value>ハイエンドＧＰ
ＥＸ１シリーズに
ᜀ挑戦᠀ちょうせんᤀすることができるᜀ証᠀あかしᤀ</Value>
        </BtxtString>
      </Values>
    </BtxtLabel>
    <BtxtLabel>
      <Key>ITEM_TEXT_045</Key>
      <Values>
        <BtxtString>
          <Id>757728019</Id>
          <Value>ハイエンドＧＰ
ＥＸ２シリーズに
ᜀ挑戦᠀ちょうせんᤀすることができるᜀ証᠀あかしᤀ</Value>
        </BtxtString>
      </Values>
    </BtxtLabel>
    <BtxtLabel>
      <Key>ITEM_TEXT_046</Key>
      <Values>
        <BtxtString>
          <Id>774505235</Id>
          <Value>ハイエンドＧＰ
ＥＸ３シリーズに
ᜀ挑戦᠀ちょうせんᤀすることができるᜀ証᠀あかしᤀ</Value>
        </BtxtString>
      </Values>
    </BtxtLabel>
    <BtxtLabel>
      <Key>ITEM_TEXT_047</Key>
      <Values>
        <BtxtString>
          <Id>791282451</Id>
          <Value>ハイエンドＧＰ
ＥＸ４シリーズに
ᜀ挑戦᠀ちょうせんᤀすることができるᜀ証᠀あかしᤀ</Value>
        </BtxtString>
      </Values>
    </BtxtLabel>
    <BtxtLabel>
      <Key>ITEM_TEXT_048</Key>
      <Values>
        <BtxtString>
          <Id>808190739</Id>
          <Value>ハイエンドＧＰ
ファイナルシリーズに
ᜀ挑戦᠀ちょうせんᤀすることができるᜀ証᠀あかしᤀ</Value>
        </BtxtString>
      </Values>
    </BtxtLabel>
    <BtxtLabel>
      <Key>ITEM_TEXT_049</Key>
      <Values>
        <BtxtString>
          <Id>822214912</Id>
          <Value />
        </BtxtString>
      </Values>
    </BtxtLabel>
    <BtxtLabel>
      <Key>ITEM_TEXT_050</Key>
      <Values>
        <BtxtString>
          <Id>838992128</Id>
          <Value />
        </BtxtString>
      </Values>
    </BtxtLabel>
    <BtxtLabel>
      <Key>ITEM_TEXT_051</Key>
      <Values>
        <BtxtString>
          <Id>858915603</Id>
          <Value>ヒフミがᜀ丘᠀おかᤀの
ARフィールドにある　ᜀ電話機᠀でんわきᤀを
ᜀ直᠀なおᤀすための　パーツ</Value>
        </BtxtString>
      </Values>
    </BtxtLabel>
    <BtxtLabel>
      <Key>ITEM_TEXT_052</Key>
      <Values>
        <BtxtString>
          <Id>876741398</Id>
          <Value>モバイルショップで
ᜀ充電᠀じゅうでんᤀケーブルと　ᜀ交換᠀こうかんᤀできる
おねえさんの　おᜀ使᠀つかᤀいで　ᜀ使᠀つかᤀうもの</Value>
        </BtxtString>
      </Values>
    </BtxtLabel>
    <BtxtLabel>
      <Key>ITEM_TEXT_053</Key>
      <Values>
        <BtxtString>
          <Id>892994323</Id>
          <Value>ᜀ引換券᠀ひきかえけんᤀと　ᜀ交換᠀こうかんᤀした
ᜀ充電᠀じゅうでんᤀケーブル
おねえさんへの　ᜀ届᠀とどᤀけもの</Value>
        </BtxtString>
      </Values>
    </BtxtLabel>
    <BtxtLabel>
      <Key>ITEM_TEXT_054</Key>
      <Values>
        <BtxtString>
          <Id>910951189</Id>
          <Value>ᜀ仮発行᠀かりはっこうᤀの　ᜀ挑戦権᠀ちょうせんけんᤀ
「Ｄランクマスターᜀ頂戦巻᠀ちょうせんけんᤀ」と
チラシのᜀ裏᠀うらᤀに　ᜀ書᠀かᤀかれている…</Value>
        </BtxtString>
      </Values>
    </BtxtLabel>
    <BtxtLabel>
      <Key>ITEM_TEXT_055</Key>
      <Values>
        <BtxtString>
          <Id>924975632</Id>
          <Value>コソモンの　ᜀ大切᠀たいせつᤀなバッジ
なんの　バッジなんだろう？</Value>
        </BtxtString>
      </Values>
    </BtxtLabel>
    <BtxtLabel>
      <Key>ITEM_TEXT_056</Key>
      <Values>
        <BtxtString>
          <Id>945029916</Id>
          <Value>ᜀ水質研究所᠀　すいしつけんきゅうじょᤀの　アクセスにᜀ使᠀つかᤀう
セキュリティの　ᜀ解除᠀かいじょᤀコード…
ᜀ取᠀とᤀりᜀ扱᠀あつかᤀいには　ᜀ注意᠀ちゅういᤀ！</Value>
        </BtxtString>
      </Values>
    </BtxtLabel>
    <BtxtLabel>
      <Key>ITEM_TEXT_057</Key>
      <Values>
        <BtxtString>
          <Id>959841041</Id>
          <Value>ミハマᜀ団᠀だんᤀの　ᜀ団員᠀だんいんᤀバッジ
リーダー　リョウジに
ᜀ認᠀みとᤀめられた　ᜀ証᠀あかしᤀ</Value>
        </BtxtString>
      </Values>
    </BtxtLabel>
    <BtxtLabel>
      <Key>ITEM_TEXT_058</Key>
      <Values>
        <BtxtString>
          <Id>975307533</Id>
          <Value>ＡＲダンジョンで　ひろった
ナゾの　ピース
いったい　なんだろう？</Value>
        </BtxtString>
      </Values>
    </BtxtLabel>
    <BtxtLabel>
      <Key>ITEM_TEXT_059</Key>
      <Values>
        <BtxtString>
          <Id>994181907</Id>
          <Value>ᜀ学校᠀がっこうᤀの　セキュリティを
ᜀ解除᠀かいじょᤀするための　プログラム
ᜀ赤᠀あかᤀい　シャッターを　ᜀ開᠀あᤀけられる！</Value>
        </BtxtString>
      </Values>
    </BtxtLabel>
    <BtxtLabel>
      <Key>ITEM_TEXT_060</Key>
      <Values>
        <BtxtString>
          <Id>1010959123</Id>
          <Value>ᜀ学校᠀がっこうᤀの　セキュリティを
ᜀ解除᠀かいじょᤀするための　プログラム
ᜀ青᠀あおᤀい　シャッターを　ᜀ開᠀あᤀけられる！</Value>
        </BtxtString>
      </Values>
    </BtxtLabel>
    <BtxtLabel>
      <Key>ITEM_TEXT_061</Key>
      <Values>
        <BtxtString>
          <Id>1027605266</Id>
          <Value>ミハマᜀ港᠀こうᤀ　ᜀ名物᠀めいぶつᤀのクレープ
ᜀ中᠀なかᤀに　ガッチモナカが　はいってる
サクサクふわふわで　おいしそう…</Value>
        </BtxtString>
      </Values>
    </BtxtLabel>
    <BtxtLabel>
      <Key>ITEM_TEXT_062</Key>
      <Values>
        <BtxtString>
          <Id>1041105165</Id>
          <Value>イベントアイテム12の説明</Value>
        </BtxtString>
      </Values>
    </BtxtLabel>
    <BtxtLabel>
      <Key>ITEM_TEXT_063</Key>
      <Values>
        <BtxtString>
          <Id>1057882381</Id>
          <Value>イベントアイテム13の説明</Value>
        </BtxtString>
      </Values>
    </BtxtLabel>
    <BtxtLabel>
      <Key>ITEM_TEXT_064</Key>
      <Values>
        <BtxtString>
          <Id>1074659597</Id>
          <Value>イベントアイテム14の説明</Value>
        </BtxtString>
      </Values>
    </BtxtLabel>
    <BtxtLabel>
      <Key>ITEM_TEXT_065</Key>
      <Values>
        <BtxtString>
          <Id>1091436813</Id>
          <Value>イベントアイテム15の説明</Value>
        </BtxtString>
      </Values>
    </BtxtLabel>
    <BtxtLabel>
      <Key>ITEM_TEXT_066</Key>
      <Values>
        <BtxtString>
          <Id>1108214029</Id>
          <Value>イベントアイテム16の説明</Value>
        </BtxtString>
      </Values>
    </BtxtLabel>
    <BtxtLabel>
      <Key>ITEM_TEXT_067</Key>
      <Values>
        <BtxtString>
          <Id>1124991245</Id>
          <Value>イベントアイテム17の説明</Value>
        </BtxtString>
      </Values>
    </BtxtLabel>
    <BtxtLabel>
      <Key>ITEM_TEXT_068</Key>
      <Values>
        <BtxtString>
          <Id>1141768461</Id>
          <Value>イベントアイテム18の説明</Value>
        </BtxtString>
      </Values>
    </BtxtLabel>
    <BtxtLabel>
      <Key>ITEM_TEXT_069</Key>
      <Values>
        <BtxtString>
          <Id>1158545677</Id>
          <Value>イベントアイテム19の説明</Value>
        </BtxtString>
      </Values>
    </BtxtLabel>
    <BtxtLabel>
      <Key>ITEM_TEXT_070</Key>
      <Values>
        <BtxtString>
          <Id>1175322893</Id>
          <Value>イベントアイテム20の説明</Value>
        </BtxtString>
      </Values>
    </BtxtLabel>
    <BtxtLabel>
      <Key>ITEM_TEXT_071</Key>
      <Values>
        <BtxtString>
          <Id>1192100109</Id>
          <Value>イベントアイテム21の説明</Value>
        </BtxtString>
      </Values>
    </BtxtLabel>
    <BtxtLabel>
      <Key>ITEM_TEXT_072</Key>
      <Values>
        <BtxtString>
          <Id>1208877325</Id>
          <Value>イベントアイテム22の説明</Value>
        </BtxtString>
      </Values>
    </BtxtLabel>
    <BtxtLabel>
      <Key>ITEM_TEXT_073</Key>
      <Values>
        <BtxtString>
          <Id>1225654541</Id>
          <Value>イベントアイテム23の説明</Value>
        </BtxtString>
      </Values>
    </BtxtLabel>
    <BtxtLabel>
      <Key>ITEM_TEXT_074</Key>
      <Values>
        <BtxtString>
          <Id>1242431757</Id>
          <Value>イベントアイテム24の説明</Value>
        </BtxtString>
      </Values>
    </BtxtLabel>
    <BtxtLabel>
      <Key>ITEM_TEXT_075</Key>
      <Values>
        <BtxtString>
          <Id>1259208973</Id>
          <Value>イベントアイテム25の説明</Value>
        </BtxtString>
      </Values>
    </BtxtLabel>
    <BtxtLabel>
      <Key>ITEM_TEXT_076</Key>
      <Values>
        <BtxtString>
          <Id>1275986189</Id>
          <Value>イベントアイテム26の説明</Value>
        </BtxtString>
      </Values>
    </BtxtLabel>
    <BtxtLabel>
      <Key>ITEM_TEXT_077</Key>
      <Values>
        <BtxtString>
          <Id>1292763405</Id>
          <Value>イベントアイテム27の説明</Value>
        </BtxtString>
      </Values>
    </BtxtLabel>
    <BtxtLabel>
      <Key>ITEM_TEXT_078</Key>
      <Values>
        <BtxtString>
          <Id>1309540621</Id>
          <Value>イベントアイテム28の説明</Value>
        </BtxtString>
      </Values>
    </BtxtLabel>
    <BtxtLabel>
      <Key>ITEM_TEXT_079</Key>
      <Values>
        <BtxtString>
          <Id>1326317837</Id>
          <Value>イベントアイテム29の説明</Value>
        </BtxtString>
      </Values>
    </BtxtLabel>
    <BtxtLabel>
      <Key>ITEM_TEXT_080</Key>
      <Values>
        <BtxtString>
          <Id>1343095053</Id>
          <Value>イベントアイテム30の説明</Value>
        </BtxtString>
      </Values>
    </BtxtLabel>
    <BtxtLabel>
      <Key>ITEM_TEXT_081</Key>
      <Values>
        <BtxtString>
          <Id>1359872269</Id>
          <Value>イベントアイテム31の説明</Value>
        </BtxtString>
      </Values>
    </BtxtLabel>
    <BtxtLabel>
      <Key>ITEM_TEXT_082</Key>
      <Values>
        <BtxtString>
          <Id>1376649485</Id>
          <Value>イベントアイテム32の説明</Value>
        </BtxtString>
      </Values>
    </BtxtLabel>
    <BtxtLabel>
      <Key>ITEM_TEXT_083</Key>
      <Values>
        <BtxtString>
          <Id>1393426701</Id>
          <Value>イベントアイテム33の説明</Value>
        </BtxtString>
      </Values>
    </BtxtLabel>
    <BtxtLabel>
      <Key>ITEM_TEXT_084</Key>
      <Values>
        <BtxtString>
          <Id>1410203917</Id>
          <Value>イベントアイテム34の説明</Value>
        </BtxtString>
      </Values>
    </BtxtLabel>
    <BtxtLabel>
      <Key>ITEM_TEXT_085</Key>
      <Values>
        <BtxtString>
          <Id>1426981133</Id>
          <Value>イベントアイテム35の説明</Value>
        </BtxtString>
      </Values>
    </BtxtLabel>
    <BtxtLabel>
      <Key>ITEM_TEXT_086</Key>
      <Values>
        <BtxtString>
          <Id>1443758349</Id>
          <Value>イベントアイテム36の説明</Value>
        </BtxtString>
      </Values>
    </BtxtLabel>
    <BtxtLabel>
      <Key>ITEM_TEXT_087</Key>
      <Values>
        <BtxtString>
          <Id>1460535565</Id>
          <Value>イベントアイテム37の説明</Value>
        </BtxtString>
      </Values>
    </BtxtLabel>
    <BtxtLabel>
      <Key>ITEM_TEXT_088</Key>
      <Values>
        <BtxtString>
          <Id>1477312781</Id>
          <Value>イベントアイテム38の説明</Value>
        </BtxtString>
      </Values>
    </BtxtLabel>
    <BtxtLabel>
      <Key>ITEM_TEXT_089</Key>
      <Values>
        <BtxtString>
          <Id>1494089997</Id>
          <Value>イベントアイテム39の説明</Value>
        </BtxtString>
      </Values>
    </BtxtLabel>
    <BtxtLabel>
      <Key>ITEM_TEXT_090</Key>
      <Values>
        <BtxtString>
          <Id>1510867213</Id>
          <Value>イベントアイテム40の説明</Value>
        </BtxtString>
      </Values>
    </BtxtLabel>
    <BtxtLabel>
      <Key>ITEM_TEXT_091</Key>
      <Values>
        <BtxtString>
          <Id>1527644429</Id>
          <Value>イベントアイテム41の説明</Value>
        </BtxtString>
      </Values>
    </BtxtLabel>
    <BtxtLabel>
      <Key>ITEM_TEXT_092</Key>
      <Values>
        <BtxtString>
          <Id>1544421645</Id>
          <Value>イベントアイテム42の説明</Value>
        </BtxtString>
      </Values>
    </BtxtLabel>
    <BtxtLabel>
      <Key>ITEM_TEXT_093</Key>
      <Values>
        <BtxtString>
          <Id>1561198861</Id>
          <Value>イベントアイテム43の説明</Value>
        </BtxtString>
      </Values>
    </BtxtLabel>
    <BtxtLabel>
      <Key>ITEM_TEXT_094</Key>
      <Values>
        <BtxtString>
          <Id>1577976077</Id>
          <Value>イベントアイテム44の説明</Value>
        </BtxtString>
      </Values>
    </BtxtLabel>
    <BtxtLabel>
      <Key>ITEM_TEXT_095</Key>
      <Values>
        <BtxtString>
          <Id>1594753293</Id>
          <Value>イベントアイテム45の説明</Value>
        </BtxtString>
      </Values>
    </BtxtLabel>
    <BtxtLabel>
      <Key>ITEM_TEXT_096</Key>
      <Values>
        <BtxtString>
          <Id>1611530509</Id>
          <Value>イベントアイテム46の説明</Value>
        </BtxtString>
      </Values>
    </BtxtLabel>
    <BtxtLabel>
      <Key>ITEM_TEXT_097</Key>
      <Values>
        <BtxtString>
          <Id>1628307725</Id>
          <Value>イベントアイテム47の説明</Value>
        </BtxtString>
      </Values>
    </BtxtLabel>
    <BtxtLabel>
      <Key>ITEM_TEXT_098</Key>
      <Values>
        <BtxtString>
          <Id>1645084941</Id>
          <Value>イベントアイテム48の説明</Value>
        </BtxtString>
      </Values>
    </BtxtLabel>
    <BtxtLabel>
      <Key>ITEM_TEXT_099</Key>
      <Values>
        <BtxtString>
          <Id>1661862157</Id>
          <Value>イベントアイテム49の説明</Value>
        </BtxtString>
      </Values>
    </BtxtLabel>
  </Labels>
</BtxtFile>